{
  "prospect_id": "temp_0ab26bec-d9e1-49b3-992c-9c38a243e098",
  "name": "Simon Taylor, CFA",
  "about": "Simon Taylor is an Associate Director and FX Trader at RBC Investor Services based in Toronto, Ontario, Canada, with relevant licenses and certifications.",
  "platforms": [
    "linkedin"
  ],
  "emails": [],
  "phones": [],
  "websites": [],
  "profile_urls": {
    "linkedin": "https://ca.linkedin.com/in/simonjamestaylor"
  },
  "location": {
    "full_address": "Toronto, Ontario, Canada",
    "city": "Toronto",
    "country": "Canada"
  },
  "discovery_confidence": 0.3,
  "created_at": "2026-01-22T14:02:07.779638",
  "updated_at": null
}