{
  "prospect_id": "temp_1c8c5b8b-b3b9-46ea-822f-420a4f870791",
  "name": "Josh Leimbach",
  "about": "Day trading the foreign currency market. Uses technical analysis to buy or sell. Focused on compounding profit for retirement rather than income.",
  "platforms": [
    "linkedin"
  ],
  "emails": [],
  "phones": [],
  "websites": [],
  "profile_urls": {
    "linkedin": "https://www.linkedin.com/in/joshleimbach"
  },
  "location": {},
  "discovery_confidence": 0.15,
  "created_at": "2026-01-22T14:02:07.779491",
  "updated_at": null
}